{
  "name": "David Bruschke",
  "firstName": "David",
  "lastName": "Bruschke",
  "email": "david.bruschke@gmail.com",
  "phone": "",
  "skills": [
    "TensorFlow",
    "Transfer Learning",
    "Machine Learning"
  ],
  "languages": [
    {
      "name": "english",
      "level": "ProfessionalWorking"
    },
    {
      "name": "dutch",
      "level": "ProfessionalWorking"
    }
  ],
  "certifications": [
    "HAVO"
  ],
  "workExperience": [
    {
      "company": "Quintor",
      "title": "ICT-consultant",
      "yearStart": 2021,
      "yearEnd": "Present"
    },
    {
      "company": "SyncVR Medical",
      "title": "Student Internship",
      "yearStart": 2021,
      "yearEnd": 2021
    },
    {
      "company": "Result! Data.ai",
      "title": "Internship",
      "yearStart": 2019,
      "yearEnd": 2020
    }
  ],
  "education": [
    {
      "institution": "De Haagse Hogeschool / The Hague University of Applied Sciences",
      "title": "Bachelor's degree, Informatica (Software engineering) / Hogere opleiding Software engineer",
      "yearFinished": 2021
    },
    {
      "institution": "De Haagse Hogeschool / The Hague University of Applied Sciences",
      "title": "Propedeuse Jaar, HBO - ICT",
      "yearFinished": 2018
    },
    {
      "institution": "Fioretti College Lisse"
    }
  ]
}